airflow_gaarf
