Metadata-Version: 2.1
Name: airflow-google-ads-api-report-fetcher
Version: 0.0.7
Summary: Library for running google-ads-api-report-fetcher in Apache Airflow.
Home-page: https://github.com/google/ads-api-reports-fetcher/py/gaarf_airflow/
Author: Google Inc. (gTech gPS CSE team)
Author-email: no-reply@google.com
License: Apache 2.0
Classifier: Programming Language :: Python :: 3
Classifier: Intended Audience :: Developers
Classifier: Topic :: Software Development :: Libraries :: Python Modules
Classifier: Operating System :: OS Independent
Classifier: License :: OSI Approved :: Apache Software License
